ertool/__init__.py
ertool/er.py
ERTool-0.3.3.dist-info/LICENSE
ERTool-0.3.3.dist-info/METADATA
ERTool-0.3.3.dist-info/WHEEL
ERTool-0.3.3.dist-info/top_level.txt
ERTool-0.3.3.dist-info/RECORD
