Metadata-Version: 2.1
Name: ERTool
Version: 0.3.3
Summary: ERTool: A Python Package for Efficient Implementation of the Evidential Reasoning Approach for Multi-Source Evidence Fusion
Home-page: UNKNOWN
Author: Tongyue Shi
Author-email: tyshipku@gmail.com
License: UNKNOWN
Platform: UNKNOWN
Requires-Dist: numpy
Requires-Dist: matplotlib
Requires-Dist: pandas
Requires-Dist: seaborn
